aizoo/__init__.py
aizoo/base.py
aizoo/common.py
aizoo/model_utils.py
aizoo/seed_utils.py
aizoo/torch_utils.py
aizoo/transformers_utils.py
aizoo/api/__init__.py
aizoo/api/baidu.py
aizoo/api/baidu_post.py
aizoo/clis/__init__.py
aizoo/clis/cli.py
aizoo/cv/__init__.py
aizoo/cv/data_augmentation.py
aizoo/cv/ocr.py
aizoo/explainer/ExplainerTabular.py
aizoo/explainer/ExplainerText.py
aizoo/explainer/__init__.py
aizoo/explainer/risk_predict_xgb.py
aizoo/explainer/shap.py
aizoo/nlp/README.md
aizoo/nlp/__init__.py
aizoo/nlp/data_augmentation.py
aizoo/nlp/paddlenlp_utils.py
aizoo/nlp/sentence_embedding.py
aizoo/nlp/test.py
aizoo/nlp/utils.py
aizoo/nlp/word_segment.py
aizoo/nlp/me_transformers/README.md
aizoo/nlp/me_transformers/__init__.py
aizoo/nlp/me_transformers/__pycache__/__init__.cpython-39.pyc
aizoo/nlp/models/TfidfClassifier.py
aizoo/nlp/models/__init__.py
aizoo/nlp/models/junnyu/roformer_chinese_sim_char_ft_small/config.json
aizoo/nlp/models/junnyu/roformer_chinese_sim_char_ft_small/pytorch_model.bin
aizoo/nlp/models/junnyu/roformer_chinese_sim_char_ft_small/vocab.txt
aizoo/nlp/word2vec/__init__.py
aizoo/nlp/word2vec/gensim_w2v.py
aizoo/nn/__init__.py
aizoo/nn/activations.py
aizoo/nn/layers.py
aizoo/nn/losses.py
aizoo/nn/lr_scheduler.py
aizoo/nn/metrics.py
aizoo/nn/optimizers.py
aizoo/nn/callbacks/__init__.py
aizoo/nn/callbacks/wandb_callback.py
aizoo/rec/__init__.py
aizoo/service/__init__.py
aizoo/service/app.py
aizoo/tab/__init__.py
aizoo/tab/default_params.py
aizoo/tab/eda.py
aizoo/tab/feature_selector.py
aizoo/tab/models.py
aizoo/tab/_algo_ml/__init__.py
aizoo/tab/_algo_ml/ftrl.py
aizoo/tab/_algo_ml/cv/CV.py
aizoo/tab/_algo_ml/cv/CVPlus.py
aizoo/tab/_algo_ml/cv/CatBoostClassifierCV.py
aizoo/tab/_algo_ml/cv/FMMModelCV.py
aizoo/tab/_algo_ml/cv/FMModelCV.py
aizoo/tab/_algo_ml/cv/KerasCV.py
aizoo/tab/_algo_ml/cv/LGBMClassifierCV.py
aizoo/tab/_algo_ml/cv/LogisticRegressionCV.py
aizoo/tab/_algo_ml/cv/OOF.py
aizoo/tab/_algo_ml/cv/XGBClassifierCV.py
aizoo-2022.11.1.17.47.51.dist-info/AUTHORS.rst
aizoo-2022.11.1.17.47.51.dist-info/LICENSE
aizoo-2022.11.1.17.47.51.dist-info/METADATA
aizoo-2022.11.1.17.47.51.dist-info/WHEEL
aizoo-2022.11.1.17.47.51.dist-info/entry_points.txt
aizoo-2022.11.1.17.47.51.dist-info/top_level.txt
aizoo-2022.11.1.17.47.51.dist-info/RECORD
