Metadata-Version: 2.1
Name: aizoo
Version: 2022.11.1.17.47.51
Summary: ai tools
Home-page: https://github.com/Jie-Yuan/aizoo
Author: Betterme
Author-email: yuanjie@example.com
License: MIT license
Keywords: aizoo
Platform: UNKNOWN
Classifier: Development Status :: 2 - Pre-Alpha
Classifier: Intended Audience :: Developers
Classifier: License :: OSI Approved :: MIT License
Classifier: Natural Language :: English
Classifier: Programming Language :: Python :: 3
Classifier: Programming Language :: Python :: 3.6
Classifier: Programming Language :: Python :: 3.7
Classifier: Programming Language :: Python :: 3.8
Requires-Python: >=3.6
License-File: LICENSE
License-File: AUTHORS.rst
Requires-Dist: meutils
Requires-Dist: missingno
Requires-Dist: pandas-summary
